mqt/problemsolver/__init__.py
mqt/problemsolver/csp.py
mqt/problemsolver/tsp.py
mqt/problemsolver/partialcompiler/evaluator.py
mqt/problemsolver/partialcompiler/qaoa.py
mqt/problemsolver/satellitesolver/ImagingLocation.py
mqt/problemsolver/satellitesolver/__init__.py
mqt/problemsolver/satellitesolver/algorithms.py
mqt/problemsolver/satellitesolver/evaluator.py
mqt/problemsolver/satellitesolver/utils.py
mqt.problemsolver-0.3.0.dist-info/METADATA
mqt.problemsolver-0.3.0.dist-info/WHEEL
mqt.problemsolver-0.3.0.dist-info/top_level.txt
mqt.problemsolver-0.3.0.dist-info/RECORD
