Metadata-Version: 2.1
Name: mqt.problemsolver
Version: 0.3.0
Summary: MQT ProblemSolver - A MQT tool for Solving Problems Using Quantum Computing
Author-email: Nils Quetschlich <nils.quetschlich@tum.de>, Lukas Burgholzer <lukas.burgholzer@jku.at>
Project-URL: Homepage, https://github.com/cda-tum/mqtproblemsolver
Project-URL: Bug Tracker, https://github.com/cda-tum/mqtproblemsolver/issues
Project-URL: Discussions, https://github.com/cda-tum/mqtproblemsolver/discussions
Project-URL: Research, https://www.cda.cit.tum.de/research/quantum/
Keywords: MQT,quantum computing
Classifier: Development Status :: 4 - Beta
Classifier: Intended Audience :: Developers
Classifier: License :: OSI Approved :: MIT License
Classifier: Operating System :: Microsoft :: Windows
Classifier: Operating System :: MacOS
Classifier: Operating System :: POSIX :: Linux
Classifier: Programming Language :: Python :: 3 :: Only
Classifier: Programming Language :: Python :: 3.8
Classifier: Programming Language :: Python :: 3.9
Classifier: Programming Language :: Python :: 3.10
Classifier: Programming Language :: Python :: 3.11
Classifier: Intended Audience :: Science/Research
Classifier: Natural Language :: English
Classifier: Topic :: Scientific/Engineering :: Electronic Design Automation (EDA)
Requires-Python: >=3.8
Requires-Dist: qiskit <0.42.0,>=0.36.0
Requires-Dist: joblib
Requires-Dist: numpy
Requires-Dist: matplotlib
Requires-Dist: mqt.ddsim
Requires-Dist: networkx
Requires-Dist: python-tsp
Requires-Dist: docplex
Requires-Dist: qiskit-optimization
Provides-Extra: coverage
Requires-Dist: mqt.problemsolver[test] ; extra == 'coverage'
Requires-Dist: coverage[toml] ~=6.5.0 ; extra == 'coverage'
Requires-Dist: pytest-cov ~=4.0.0 ; extra == 'coverage'
Provides-Extra: dev
Requires-Dist: mqt.problemsolver[coverage] ; extra == 'dev'
Provides-Extra: test
Requires-Dist: pytest >=7 ; extra == 'test'
